GEMATRIA/__init__.py
GEMATRIA/converter.py
GEMATRIA/model.py
GEMATRIA/nmf.py
GEMATRIA/plot.py
OMEGA_core/__init__.py
OMEGA_core/boundary.py
OMEGA_core/cell.py
OMEGA_core/cluster.py
OMEGA_core/config.py
OMEGA_core/helper.py
OMEGA_core/image.py
OMEGA_core/io.py
OMEGA_core/measure.py
OMEGA_core/metrics.py
OMEGA_core/plot.py
OMEGA_micro-0.0.2.dist-info/LICENSE
OMEGA_micro-0.0.2.dist-info/METADATA
OMEGA_micro-0.0.2.dist-info/WHEEL
OMEGA_micro-0.0.2.dist-info/top_level.txt
OMEGA_micro-0.0.2.dist-info/RECORD
