Metadata-Version: 2.1
Name: OMEGA-micro
Version: 0.0.2
Summary: Open source, Mycobacteria-Enhanced Graphic Analysis toolkit
Home-page: UNKNOWN
Author: jz-rolling
Author-email: juzhu@hsph.harvard.edu
License: UNKNOWN
Platform: UNKNOWN
Classifier: Programming Language :: Python :: 3
Classifier: License :: OSI Approved :: MIT License
Classifier: Operating System :: OS Independent
Requires-Python: >=3.6
